Workbook

Sheet FP
G6: CONSUMO (KWH) | H6: FACTOR DE POTENCIA | I6: CONSUMO (KVAH) | J6: RECARGO/BONIFICACIÓN FACTOR DE POTENCIA | K6: KVArh | M6: RECARGO FP | N6: BONIFICACIÓN FP
B7: =ACOS(H7/100) -> 0.1114129 | C7: =B7*(360/(2*3.1416)) -> 6.3834741 | F7: ENERO | G7: ='CON FACTOR DE POTENCIA '!G4 -> 22737 | H7: ='CON FACTOR DE POTENCIA '!H4 -> 99.38 | I7: ='CON FACTOR DE POTENCIA '!I4 -> 22879 | J7: =ROUNDUP(IF(H7<90,M7,N7),2) -> 2.36 | K7: ='CON FACTOR DE POTENCIA '!O4 -> 2544 | M7: =ROUNDUP(IF((3/5)*((90/H7)-1)*100<=120,((3/5)*((90/H7)-1))*(-1)*100,-120),2) -> 5.67 | N7: =((1/4)*((1-(90/H7))))*100 -> 2.3596297
B8: =ACOS(H8/100) -> 0.11923437 | C8: =B8*(360/(2*3.1416)) -> 6.8316103 | D8: =G7/I7 -> 0.99379344 | F8: FEBRERO | G8: ='CON FACTOR DE POTENCIA '!G5 -> 22194 | H8: ='CON FACTOR DE POTENCIA '!H5 -> 99.29 | I8: ='CON FACTOR DE POTENCIA '!I5 -> 22353 | J8: =ROUNDUP(IF(H8<90,M8,N8),2) -> 2.34 | K8: ='CON FACTOR DE POTENCIA '!O5 -> 2659 | M8: =ROUNDUP(IF((3/5)*((90/H8)-1)*100<=120,((3/5)*((90/H8)-1))*(-1)*100,-120),2) -> 5.62 | N8: =((1/4)*((1-(90/H8))))*100 -> 2.3391077
B9: =ACOS(H9/100) -> 0.15047489 | C9: =B9*(360/(2*3.1416)) -> 8.6215559 | F9: MARZO | G9: ='CON FACTOR DE POTENCIA '!G6 -> 25938 | H9: ='CON FACTOR DE POTENCIA '!H6 -> 98.87 | I9: ='CON FACTOR DE POTENCIA '!I6 -> 26235 | J9: =ROUNDUP(IF(H9<90,M9,N9),2) -> 2.25 | K9: ='CON FACTOR DE POTENCIA '!O6 -> 3933 | M9: =ROUNDUP(IF((3/5)*((90/H9)-1)*100<=120,((3/5)*((90/H9)-1))*(-1)*100,-120),2) -> 5.39 | N9: =((1/4)*((1-(90/H9))))*100 -> 2.2428441
B10: =ACOS(H10/100) -> 0.17342232 | C10: =B10*(360/(2*3.1416)) -> 9.9363438 | F10: ABRIL | G10: ='CON FACTOR DE POTENCIA '!G7 -> 29570 | H10: ='CON FACTOR DE POTENCIA '!H7 -> 98.5 | I10: ='CON FACTOR DE POTENCIA '!I7 -> 30021 | J10: =ROUNDUP(IF(H10<90,M10,N10),2) -> 2.16 | K10: ='CON FACTOR DE POTENCIA '!O7 -> 5181 | M10: =ROUNDUP(IF((3/5)*((90/H10)-1)*100<=120,((3/5)*((90/H10)-1))*(-1)*100,-120),2) -> 5.18 | N10: =((1/4)*((1-(90/H10))))*100 -> 2.1573604
B11: =ACOS(H11/100) -> 0.197297 | C11: =B11*(360/(2*3.1416)) -> 11.304259 | F11: MAYO | G11: ='CON FACTOR DE POTENCIA '!G8 -> 37186 | H11: ='CON FACTOR DE POTENCIA '!H8 -> 98.06 | I11: ='CON FACTOR DE POTENCIA '!I8 -> 37922 | J11: =ROUNDUP(IF(H11<90,M11,N11),2) -> 2.06 | K11: ='CON FACTOR DE POTENCIA '!O8 -> 7434 | M11: =ROUNDUP(IF((3/5)*((90/H11)-1)*100<=120,((3/5)*((90/H11)-1))*(-1)*100,-120),2) -> 4.94 | N11: =((1/4)*((1-(90/H11))))*100 -> 2.0548644
B12: =ACOS(H12/100) -> 0.22090295 | C12: =B12*(360/(2*3.1416)) -> 12.656777 | F12: JUNIO | G12: ='CON FACTOR DE POTENCIA '!G9 -> 41697 | H12: ='CON FACTOR DE POTENCIA '!H9 -> 97.57 | I12: ='CON FACTOR DE POTENCIA '!I9 -> 42736 | J12: =ROUNDUP(IF(H12<90,M12,N12),2) -> 1.94 | K12: ='CON FACTOR DE POTENCIA '!O9 -> 9364 | M12: =ROUNDUP(IF((3/5)*((90/H12)-1)*100<=120,((3/5)*((90/H12)-1))*(-1)*100,-120),2) -> 4.66 | N12: =((1/4)*((1-(90/H12))))*100 -> 1.9396331
B13: =ACOS(H13/100) -> 0.23116561 | C13: =B13*(360/(2*3.1416)) -> 13.244783 | F13: JULIO | G13: ='CON FACTOR DE POTENCIA '!G10 -> 44080 | H13: ='CON FACTOR DE POTENCIA '!H10 -> 97.34 | I13: ='CON FACTOR DE POTENCIA '!I10 -> 45285 | J13: =ROUNDUP(IF(H13<90,M13,N13),2) -> 1.89 | K13: ='CON FACTOR DE POTENCIA '!O10 -> 10376 | M13: =ROUNDUP(IF((3/5)*((90/H13)-1)*100<=120,((3/5)*((90/H13)-1))*(-1)*100,-120),2) -> 4.53 | N13: =((1/4)*((1-(90/H13))))*100 -> 1.8851449
B14: =ACOS(H14/100) -> 0.21062709 | C14: =B14*(360/(2*3.1416)) -> 12.068015 | F14: AGOSTO | G14: ='CON FACTOR DE POTENCIA '!G11 -> 45544 | H14: ='CON FACTOR DE POTENCIA '!H11 -> 97.79 | I14: ='CON FACTOR DE POTENCIA '!I11 -> 46574 | J14: =ROUNDUP(IF(H14<90,M14,N14),2) -> 2 | K14: ='CON FACTOR DE POTENCIA '!O11 -> 9738 | M14: =ROUNDUP(IF((3/5)*((90/H14)-1)*100<=120,((3/5)*((90/H14)-1))*(-1)*100,-120),2) -> 4.78 | N14: =((1/4)*((1-(90/H14))))*100 -> 1.9915124
B15: =ACOS(H15/100) -> 0.20870524 | C15: =B15*(360/(2*3.1416)) -> 11.957902 | F15: SEPTIEMBRE | G15: ='CON FACTOR DE POTENCIA '!G12 -> 44054 | H15: ='CON FACTOR DE POTENCIA '!H12 -> 97.83 | I15: ='CON FACTOR DE POTENCIA '!I12 -> 45032 | J15: =ROUNDUP(IF(H15<90,M15,N15),2) -> 2.01 | K15: ='CON FACTOR DE POTENCIA '!O12 -> 9331 | M15: =ROUNDUP(IF((3/5)*((90/H15)-1)*100<=120,((3/5)*((90/H15)-1))*(-1)*100,-120),2) -> 4.81 | N15: =((1/4)*((1-(90/H15))))*100 -> 2.00092
B16: =ACOS(H16/100) -> 0.20033484 | C16: =B16*(360/(2*3.1416)) -> 11.478314 | F16: OCTUBRE | G16: ='CON FACTOR DE POTENCIA '!G13 -> 45016 | H16: ='CON FACTOR DE POTENCIA '!H13 -> 98 | I16: ='CON FACTOR DE POTENCIA '!I13 -> 45935 | J16: =ROUNDUP(IF(H16<90,M16,N16),2) -> 2.05 | K16: ='CON FACTOR DE POTENCIA '!O13 -> 9141 | M16: =ROUNDUP(IF((3/5)*((90/H16)-1)*100<=120,((3/5)*((90/H16)-1))*(-1)*100,-120),2) -> 4.9 | N16: =((1/4)*((1-(90/H16))))*100 -> 2.0408163
B17: =ACOS(H17/100) -> 0.16079696 | C17: =B17*(360/(2*3.1416)) -> 9.2129655 | F17: NOVIEMBRE | G17: ='CON FACTOR DE POTENCIA '!G14 -> 33840 | H17: ='CON FACTOR DE POTENCIA '!H14 -> 98.71 | I17: ='CON FACTOR DE POTENCIA '!I14 -> 34283 | J17: =ROUNDUP(IF(H17<90,M17,N17),2) -> 2.21 | K17: ='CON FACTOR DE POTENCIA '!O14 -> 5489 | M17: =ROUNDUP(IF((3/5)*((90/H17)-1)*100<=120,((3/5)*((90/H17)-1))*(-1)*100,-120),2) -> 5.3 | N17: =((1/4)*((1-(90/H17))))*100 -> 2.2059568
B18: =ACOS(H18/100) -> 0.19212863 | C18: =B18*(360/(2*3.1416)) -> 11.008134 | F18: DICIEMBRE | G18: ='CON FACTOR DE POTENCIA '!G15 -> 30641 | H18: ='CON FACTOR DE POTENCIA '!H15 -> 98.16 | I18: ='CON FACTOR DE POTENCIA '!I15 -> 31216 | J18: =ROUNDUP(IF(H18<90,M18,N18),2) -> 2.08 | K18: ='CON FACTOR DE POTENCIA '!O15 -> 5961 | M18: =ROUNDUP(IF((3/5)*((90/H18)-1)*100<=120,((3/5)*((90/H18)-1))*(-1)*100,-120),2) -> 4.99 | N18: =((1/4)*((1-(90/H18))))*100 -> 2.0782396
G22: CONSUMO CON FV (KWH) | H22: FACTOR DE POTENCIA CON FV | I22: CONSUMO (KVAH) | J22: RECARGO/BONIFICACIÓN FACTOR DE POTENCIA | K22: KVArh | M22: RECARGO FP | N22: BONIFICACIÓN FP
F23: ENERO | G23: ='CON FACTOR DE POTENCIA '!T4 -> 0 | H23: =ROUNDUP(IF(G23>0,(G23/I23)*100,100),2) -> 100 | I23: ='CON FACTOR DE POTENCIA '!X4 -> 2544 | J23: =ROUNDUP(IF(H23<90,M23,N23),2) -> 2.5 | K23: =K7 -> 2544 | M23: =ROUNDUP(IF((3/5)*((90/H23)-1)*100<=120,((3/5)*((90/H23)-1))*(-1)*100,-120),2) -> 6 | N23: =((1/4)*((1-(90/H23))))*100 -> 2.5
D24: =G23/I23 -> 0 | F24: FEBRERO | G24: ='CON FACTOR DE POTENCIA '!T5 -> 0 | H24: =ROUNDUP(IF(G24>0,(G24/I24)*100,100),2) -> 100 | I24: ='CON FACTOR DE POTENCIA '!X5 -> 2659 | J24: =ROUNDUP(IF(H24<90,M24,N24),2) -> 2.5 | K24: =K8 -> 2659 | M24: =ROUNDUP(IF((3/5)*((90/H24)-1)*100<=120,((3/5)*((90/H24)-1))*(-1)*100,-120),2) -> 6 | N24: =((1/4)*((1-(90/H24))))*100 -> 2.5
F25: MARZO | G25: ='CON FACTOR DE POTENCIA '!T6 -> 0 | H25: =ROUNDUP(IF(G25>0,(G25/I25)*100,100),2) -> 100 | I25: ='CON FACTOR DE POTENCIA '!X6 -> 3933 | J25: =ROUNDUP(IF(H25<90,M25,N25),2) -> 2.5 | K25: =K9 -> 3933 | M25: =ROUNDUP(IF((3/5)*((90/H25)-1)*100<=120,((3/5)*((90/H25)-1))*(-1)*100,-120),2) -> 6 | N25: =((1/4)*((1-(90/H25))))*100 -> 2.5
F26: ABRIL | G26: ='CON FACTOR DE POTENCIA '!T7 -> 0 | H26: =ROUNDUP(IF(G26>0,(G26/I26)*100,100),2) -> 100 | I26: ='CON FACTOR DE POTENCIA '!X7 -> 5181 | J26: =ROUNDUP(IF(H26<90,M26,N26),2) -> 2.5 | K26: =K10 -> 5181 | M26: =ROUNDUP(IF((3/5)*((90/H26)-1)*100<=120,((3/5)*((90/H26)-1))*(-1)*100,-120),2) -> 6 | N26: =((1/4)*((1-(90/H26))))*100 -> 2.5
D27: =SQRT((G23^2)+(K23^2)) -> 2544 | F27: MAYO | G27: ='CON FACTOR DE POTENCIA '!T8 -> 0 | H27: =ROUNDUP(IF(G27>0,(G27/I27)*100,100),2) -> 100 | I27: ='CON FACTOR DE POTENCIA '!X8 -> 7434 | J27: =ROUNDUP(IF(H27<90,M27,N27),2) -> 2.5 | K27: =K11 -> 7434 | M27: =ROUNDUP(IF((3/5)*((90/H27)-1)*100<=120,((3/5)*((90/H27)-1))*(-1)*100,-120),2) -> 6 | N27: =((1/4)*((1-(90/H27))))*100 -> 2.5
F28: JUNIO | G28: ='CON FACTOR DE POTENCIA '!T9 -> 0 | H28: =ROUNDUP(IF(G28>0,(G28/I28)*100,100),2) -> 100 | I28: ='CON FACTOR DE POTENCIA '!X9 -> 9364 | J28: =ROUNDUP(IF(H28<90,M28,N28),2) -> 2.5 | K28: =K12 -> 9364 | M28: =ROUNDUP(IF((3/5)*((90/H28)-1)*100<=120,((3/5)*((90/H28)-1))*(-1)*100,-120),2) -> 6 | N28: =((1/4)*((1-(90/H28))))*100 -> 2.5
F29: JULIO | G29: ='CON FACTOR DE POTENCIA '!T10 -> 0 | H29: =ROUNDUP(IF(G29>0,(G29/I29)*100,100),2) -> 100 | I29: ='CON FACTOR DE POTENCIA '!X10 -> 10376 | J29: =ROUNDUP(IF(H29<90,M29,N29),2) -> 2.5 | K29: =K13 -> 10376 | M29: =ROUNDUP(IF((3/5)*((90/H29)-1)*100<=120,((3/5)*((90/H29)-1))*(-1)*100,-120),2) -> 6 | N29: =((1/4)*((1-(90/H29))))*100 -> 2.5
F30: AGOSTO | G30: ='CON FACTOR DE POTENCIA '!T11 -> 0 | H30: =ROUNDUP(IF(G30>0,(G30/I30)*100,100),2) -> 100 | I30: ='CON FACTOR DE POTENCIA '!X11 -> 9738 | J30: =ROUNDUP(IF(H30<90,M30,N30),2) -> 2.5 | K30: =K14 -> 9738 | M30: =ROUNDUP(IF((3/5)*((90/H30)-1)*100<=120,((3/5)*((90/H30)-1))*(-1)*100,-120),2) -> 6 | N30: =((1/4)*((1-(90/H30))))*100 -> 2.5
F31: SEPTIEMBRE | G31: ='CON FACTOR DE POTENCIA '!T12 -> 0 | H31: =ROUNDUP(IF(G31>0,(G31/I31)*100,100),2) -> 100 | I31: ='CON FACTOR DE POTENCIA '!X12 -> 9331 | J31: =ROUNDUP(IF(H31<90,M31,N31),2) -> 2.5 | K31: =K15 -> 9331 | M31: =ROUNDUP(IF((3/5)*((90/H31)-1)*100<=120,((3/5)*((90/H31)-1))*(-1)*100,-120),2) -> 6 | N31: =((1/4)*((1-(90/H31))))*100 -> 2.5
F32: OCTUBRE | G32: ='CON FACTOR DE POTENCIA '!T13 -> 0 | H32: =ROUNDUP(IF(G32>0,(G32/I32)*100,100),2) -> 100 | I32: ='CON FACTOR DE POTENCIA '!X13 -> 9141 | J32: =ROUNDUP(IF(H32<90,M32,N32),2) -> 2.5 | K32: =K16 -> 9141 | M32: =ROUNDUP(IF((3/5)*((90/H32)-1)*100<=120,((3/5)*((90/H32)-1))*(-1)*100,-120),2) -> 6 | N32: =((1/4)*((1-(90/H32))))*100 -> 2.5
F33: NOVIEMBRE | G33: ='CON FACTOR DE POTENCIA '!T14 -> 0 | H33: =ROUNDUP(IF(G33>0,(G33/I33)*100,100),2) -> 100 | I33: ='CON FACTOR DE POTENCIA '!X14 -> 5489 | J33: =ROUNDUP(IF(H33<90,M33,N33),2) -> 2.5 | K33: =K17 -> 5489 | M33: =ROUNDUP(IF((3/5)*((90/H33)-1)*100<=120,((3/5)*((90/H33)-1))*(-1)*100,-120),2) -> 6 | N33: =((1/4)*((1-(90/H33))))*100 -> 2.5
F34: DICIEMBRE | G34: ='CON FACTOR DE POTENCIA '!T15 -> 0 | H34: =ROUNDUP(IF(G34>0,(G34/I34)*100,100),2) -> 100 | I34: ='CON FACTOR DE POTENCIA '!X15 -> 5961 | J34: =ROUNDUP(IF(H34<90,M34,N34),2) -> 2.5 | K34: =K18 -> 5961 | M34: =ROUNDUP(IF((3/5)*((90/H34)-1)*100<=120,((3/5)*((90/H34)-1))*(-1)*100,-120),2) -> 6 | N34: =((1/4)*((1-(90/H34))))*100 -> 2.5

Sheet CON FACTOR DE POTENCIA 
D2: Cargar consumo base (kWh) de recibo | E2: Cargar consumo intermedio (kWh) de recibo | F2: Cargar consumo punta (kWh) de recibo | G2: Consumo se cargara por sí solo (kWh) | H2: Introducir dato de factor de potencia por mesen (%) | J2: Introducir demanda máxima mensual obtenida del recibo | N2: Factor de carga obtenido en el acuerdo único A/064 2018 | Q2: Obtener datos de HSP de plataforma de la NASA | AF2: ESTUDIO FV
C3: Mes | D3: Consumo base (kWh) | E3: Consumo intermedio (kWh) | F3: Coonsumo punta (kWh) | G3: CONSUMO (KWH) | H3: FACTOR DE POTENCIA | I3: CONSUMO (KVAH) | J3: DEMANDA MÁXIMA MENSUAL | K3: DEMANDA MÁXIMA EN PUNTA | L3: DEMANDA ENERGIZADA | M3: RECARGO / BONIFICACIÓN FACTOR DE POTENCIA | N3: FACTOR DE CARGA | O3: KVArh | Q3: HSP | R3: DÍAS DEL MES | S3: ENERGÍA GENERADA (kWh) | T3: CONSUMO NUEVO (KWH) | U3: Consumo nuevo base (kWh) | V3: Consumo nuevo intermedio (kWh) | W3: Coonsumo nuevo punta (kWh) | X3: CONSUMO NUEVO (KVAH) | Y3: FACTOR DE POTENCIA NUEVO | Z3: RECARGO POR NUEVO FACTOR DE POTENCIA | AA3: DEMANDA MÁXIMA MENSUAL | AB3: DEMANDA MÁXIMA EN PUNTA | AC3: DEMANDA ENERGIZADA | AE3: Eficiencia ponderada para SFV interconectado
C4: ENERO | D4: 5422 | E4: 16052 | F4: 1263 | G4: =SUM(D4:F4) -> 22737 | H4: 99.38 | I4: =ROUNDUP(G4/(H4/100),0) -> 22879 | J4: 78 | K4: 78 | L4: =ROUNDUP(G4/(24*R4*$N$4),0) -> 54 | M4: =FP!J7 -> 2.36 | N4: 0.57 | O4: =ROUNDUP(SIN(A79)*I4,0) -> 2544 | Q4: 5.6916 | R4: 31 | S4: =ROUNDDOWN(($AG$5)*$AE$5*Q4*R4,0) -> 32981 | T4: =SUM(U4:W4) -> 0 | U4: =L118 -> 0 | V4: =L102 -> 0 | W4: =N86 -> 0 | X4: =ROUNDUP(SQRT((T4^2)+(O4^2)),0) -> 2544 | Y4: =FP!H23 -> 100 | Z4: =FP!J23 -> 2.5 | AA4: =J4 -> 78 | AB4: 8 | AC4: =ROUNDUP(T4/(24*R4*$N$4),0) -> 0 | AE4: EFICIENCIA | AG4: POTENCIA A INSTALAR (KWP)
C5: FEBRERO | D5: 5293 | E5: 15668 | F5: 1233 | G5: =SUM(D5:F5) -> 22194 | H5: 99.29 | I5: =ROUNDUP(G5/(H5/100),0) -> 22353 | J5: 75 | K5: 75 | L5: =ROUNDUP(G5/(24*R5*$N$4),0) -> 58 | M5: =FP!J8 -> 2.34 | O5: =ROUNDUP(SIN(A80)*I5,0) -> 2659 | Q5: 6.4728 | R5: 28 | S5: =ROUNDDOWN(($AG$5)*$AE$5*Q5*R5,0) -> 33878 | T5: =SUM(U5:W5) -> 0 | U5: =L119 -> 0 | V5: =L103 -> 0 | W5: =N87 -> 0 | X5: =ROUNDUP(SQRT((T5^2)+(O5^2)),0) -> 2659 | Y5: =FP!H24 -> 100 | Z5: =FP!J24 -> 2.5 | AA5: =J5 -> 75 | AB5: 8 | AC5: =ROUNDUP(T5/(24*R5*$N$4),0) -> 0 | AE5: 0.75 | AG5: =(AE11*AE14)/1000 -> 249.24
C6: MARZO | D6: 6186 | E6: 18311 | F6: 1441 | G6: =SUM(D6:F6) -> 25938 | H6: 98.87 | I6: =ROUNDUP(G6/(H6/100),0) -> 26235 | J6: 73 | K6: 73 | L6: =ROUNDUP(G6/(24*R6*$N$4),0) -> 62 | M6: =FP!J9 -> 2.25 | O6: =ROUNDUP(SIN(A81)*I6,0) -> 3933 | Q6: 7.2094 | R6: 31 | S6: =ROUNDDOWN(($AG$5)*$AE$5*Q6*R6,0) -> 41777 | T6: =SUM(U6:W6) -> 0 | U6: =L120 -> 0 | V6: =L104 -> 0 | W6: =N88 -> 0 | X6: =ROUNDUP(SQRT((T6^2)+(O6^2)),0) -> 3933 | Y6: =FP!H25 -> 100 | Z6: =FP!J25 -> 2.5 | AA6: =J6 -> 73 | AB6: 8 | AC6: =ROUNDUP(T6/(24*R6*$N$4),0) -> 0
C7: ABRIL | D7: 7052 | E7: 20875 | F7: 1643 | G7: =SUM(D7:F7) -> 29570 | H7: 98.5 | I7: =ROUNDUP(G7/(H7/100),0) -> 30021 | J7: 87 | K7: 87 | L7: =ROUNDUP(G7/(24*R7*$N$4),0) -> 73 | M7: =FP!J10 -> 2.16 | O7: =ROUNDUP(SIN(A82)*I7,0) -> 5181 | Q7: 7.3445 | R7: 30 | S7: =ROUNDDOWN(($AG$5)*$AE$5*Q7*R7,0) -> 41187 | T7: =SUM(U7:W7) -> 0 | U7: =L121 -> 0 | V7: =L105 -> 0 | W7: =N89 -> 0 | X7: =ROUNDUP(SQRT((T7^2)+(O7^2)),0) -> 5181 | Y7: =FP!H26 -> 100 | Z7: =FP!J26 -> 2.5 | AA7: =J7 -> 87 | AB7: 8 | AC7: =ROUNDUP(T7/(24*R7*$N$4),0) -> 0 | AE7: POTENCIA REQUERIDA (KWP)
C8: MAYO | D8: 8868 | E8: 26252 | F8: 2066 | G8: =SUM(D8:F8) -> 37186 | H8: 98.06 | I8: =ROUNDUP(G8/(H8/100),0) -> 37922 | J8: 104 | K8: 104 | L8: =ROUNDUP(G8/(24*R8*$N$4),0) -> 88 | M8: =FP!J11 -> 2.06 | O8: =ROUNDUP(SIN(A83)*I8,0) -> 7434 | Q8: 7.0898 | R8: 31 | S8: =ROUNDDOWN(($AG$5)*$AE$5*Q8*R8,0) -> 41084 | T8: =SUM(U8:W8) -> 0 | U8: =L122 -> 0 | V8: =L106 -> 0 | W8: =N90 -> 0 | X8: =ROUNDUP(SQRT((T8^2)+(O8^2)),0) -> 7434 | Y8: =FP!H27 -> 100 | Z8: =FP!J27 -> 2.5 | AA8: =J8 -> 104 | AB8: 8 | AC8: =ROUNDUP(T8/(24*R8*$N$4),0) -> 0 | AE8: =ROUNDUP(D17/(365*Q17*AE5),2) -> 248.94
C9: JUNIO | D9: 9944 | E9: 29437 | F9: 2316 | G9: =SUM(D9:F9) -> 41697 | H9: 97.57 | I9: =ROUNDUP(G9/(H9/100),0) -> 42736 | J9: 109 | K9: 109 | L9: =ROUNDUP(G9/(24*R9*$N$4),0) -> 102 | M9: =FP!J12 -> 1.94 | O9: =ROUNDUP(SIN(A84)*I9,0) -> 9364 | Q9: 6.1498 | R9: 30 | S9: =ROUNDDOWN(($AG$5)*$AE$5*Q9*R9,0) -> 34487 | T9: =SUM(U9:W9) -> 0 | U9: =L123 -> 0 | V9: =L107 -> 0 | W9: =N91 -> 0 | X9: =ROUNDUP(SQRT((T9^2)+(O9^2)),0) -> 9364 | Y9: =FP!H28 -> 100 | Z9: =FP!J28 -> 2.5 | AA9: =J9 -> 109 | AB9: 8 | AC9: =ROUNDUP(T9/(24*R9*$N$4),0) -> 0
C10: JULIO | D10: 10512 | E10: 31120 | F10: 2448 | G10: =SUM(D10:F10) -> 44080 | H10: 97.34 | I10: =ROUNDUP(G10/(H10/100),0) -> 45285 | J10: 108 | K10: 77 | L10: =ROUNDUP(G10/(24*R10*$N$4),0) -> 104 | M10: =FP!J13 -> 1.89 | O10: =ROUNDUP(SIN(A85)*I10,0) -> 10376 | Q10: 5.5639 | R10: 31 | S10: =ROUNDDOWN(($AG$5)*$AE$5*Q10*R10,0) -> 32241 | T10: =SUM(U10:W10) -> 0 | U10: =L124 -> 0 | V10: =L108 -> 0 | W10: =N92 -> 0 | X10: =ROUNDUP(SQRT((T10^2)+(O10^2)),0) -> 10376 | Y10: =FP!H29 -> 100 | Z10: =FP!J29 -> 2.5 | AA10: =J10 -> 108 | AB10: 8 | AC10: =ROUNDUP(T10/(24*R10*$N$4),0) -> 0 | AE10: Potencia del panel (W) | AF10: Elegir potencia del panel (W)
C11: AGOSTO | D11: 10861 | E11: 32153 | F11: 2530 | G11: =SUM(D11:F11) -> 45544 | H11: 97.79 | I11: =ROUNDUP(G11/(H11/100),0) -> 46574 | J11: 109 | K11: 109 | L11: =ROUNDUP(G11/(24*R11*$N$4),0) -> 108 | M11: =FP!J14 -> 2 | O11: =ROUNDUP(SIN(A86)*I11,0) -> 9738 | Q11: 5.6366 | R11: 31 | S11: =ROUNDDOWN(($AG$5)*$AE$5*Q11*R11,0) -> 32663 | T11: =SUM(U11:W11) -> 0 | U11: =L125 -> 0 | V11: =L109 -> 0 | W11: =N93 -> 0 | X11: =ROUNDUP(SQRT((T11^2)+(O11^2)),0) -> 9738 | Y11: =FP!H30 -> 100 | Z11: =FP!J30 -> 2.5 | AA11: =J11 -> 109 | AB11: 8 | AC11: =ROUNDUP(T11/(24*R11*$N$4),0) -> 0 | AE11: 620
C12: SEPTIEMBRE | D12: 10506 | E12: 31101 | F12: 2447 | G12: =SUM(D12:F12) -> 44054 | H12: 97.83 | I12: =ROUNDUP(G12/(H12/100),0) -> 45032 | J12: 109 | K12: 109 | L12: =ROUNDUP(G12/(24*R12*$N$4),0) -> 108 | M12: =FP!J15 -> 2.01 | O12: =ROUNDUP(SIN(A87)*I12,0) -> 9331 | Q12: 5.5229 | R12: 30 | S12: =ROUNDDOWN(($AG$5)*$AE$5*Q12*R12,0) -> 30971 | T12: =SUM(U12:W12) -> 0 | U12: =L126 -> 0 | V12: =L110 -> 0 | W12: =N94 -> 0 | X12: =ROUNDUP(SQRT((T12^2)+(O12^2)),0) -> 9331 | Y12: =FP!H31 -> 100 | Z12: =FP!J31 -> 2.5 | AA12: =J12 -> 109 | AB12: 8 | AC12: =ROUNDUP(T12/(24*R12*$N$4),0) -> 0
C13: OCTUBRE | D13: 10735 | E13: 31781 | F13: 2500 | G13: =SUM(D13:F13) -> 45016 | H13: 98 | I13: =ROUNDUP(G13/(H13/100),0) -> 45935 | J13: 113 | K13: 113 | L13: =ROUNDUP(G13/(24*R13*$N$4),0) -> 107 | M13: =FP!J16 -> 2.05 | O13: =ROUNDUP(SIN(A88)*I13,0) -> 9141 | Q13: 6.3444 | R13: 31 | S13: =ROUNDDOWN(($AG$5)*$AE$5*Q13*R13,0) -> 36764 | T13: =SUM(U13:W13) -> 0 | U13: =L127 -> 0 | V13: =L111 -> 0 | W13: =N95 -> 0 | X13: =ROUNDUP(SQRT((T13^2)+(O13^2)),0) -> 9141 | Y13: =FP!H32 -> 100 | Z13: =FP!J32 -> 2.5 | AA13: =J13 -> 113 | AB13: 8 | AC13: =ROUNDUP(T13/(24*R13*$N$4),0) -> 0 | AE13: Número de paneles | AF13: Elegir cantidad de paneles
C14: NOVIEMBRE | D14: 8070 | E14: 23890 | F14: 1880 | G14: =SUM(D14:F14) -> 33840 | H14: 98.71 | I14: =ROUNDUP(G14/(H14/100),0) -> 34283 | J14: 104 | K14: 104 | L14: =ROUNDUP(G14/(24*R14*$N$4),0) -> 83 | M14: =FP!J17 -> 2.21 | O14: =ROUNDUP(SIN(A89)*I14,0) -> 5489 | Q14: 6.185 | R14: 30 | S14: =ROUNDDOWN(($AG$5)*$AE$5*Q14*R14,0) -> 34684 | T14: =SUM(U14:W14) -> 0 | U14: =L128 -> 0 | V14: =L112 -> 0 | W14: =N96 -> 0 | X14: =ROUNDUP(SQRT((T14^2)+(O14^2)),0) -> 5489 | Y14: =FP!H33 -> 100 | Z14: =FP!J33 -> 2.5 | AA14: =J14 -> 104 | AB14: 8 | AC14: =ROUNDUP(T14/(24*R14*$N$4),0) -> 0 | AE14: 402
C15: DICIEMBRE | D15: 7307 | E15: 21632 | F15: 1702 | G15: =SUM(D15:F15) -> 30641 | H15: 98.16 | I15: =ROUNDUP(G15/(H15/100),0) -> 31216 | J15: 88 | K15: 88 | L15: =ROUNDUP(G15/(24*R15*$N$4),0) -> 73 | M15: =FP!J18 -> 2.08 | O15: =ROUNDUP(SIN(A90)*I15,0) -> 5961 | Q15: 5.5872 | R15: 31 | S15: =ROUNDDOWN(($AG$5)*$AE$5*Q15*R15,0) -> 32376 | T15: =SUM(U15:W15) -> 0 | U15: =L129 -> 0 | V15: =L113 -> 0 | W15: =N97 -> 0 | X15: =ROUNDUP(SQRT((T15^2)+(O15^2)),0) -> 5961 | Y15: =FP!H34 -> 100 | Z15: =FP!J34 -> 2.5 | AA15: =J15 -> 88 | AB15: 8 | AC15: =ROUNDUP(T15/(24*R15*$N$4),0) -> 0
Q16: HSP PROMEDIO ANUAL | S16: TOTAL | U16: =SUM(U4:U15) -> 0
C17: TOTAL | D17: =SUM(G4:G15) -> 422497 | F17: =G4/I4 -> 0.99379344 | Q17: =ROUNDDOWN(AVERAGE(Q4:Q15),1) -> 6.2 | S17: =SUM(S4:S15) -> 425093
X19: MULTIPLICADORES
D20: Actualizar costos a localidad de la instalación | M20: FIJO ($) | N20: ENERGÍA BASE ($/KWH) | O20: ENERGÍAINTERMEDIO ($/KWH) | P20: ENERGÍA PUNTA ($/KWH) | Q20: DISTRIBUCIÓN ($/KW) | R20: CAPACIDAD ($/KW) | S20: CARGO BAJA TENSIÓN(2%) | T20: CARGO FACTOR DE POTENCIA | U20: TOTAL | V20: TOTAL + IVA | X20: DISTRIBUCIÓN | Y20: CAPACIDAD | AE20: =AE8/0.62 -> 401.51613
D21: FIJO ($) | E21: kWh base ($/KWH) | F21: kWh intermedio ($/KWH) | G21: kWh punta ($/KWH) | H21: DISTRIBUCIÓN ($/KW) | I21: CAPACIDAD ($/KW) | J21: BAJA TENSION (2%) | L21: ENERO | M21: =D22 -> 777.67 | N21: =D4*E22 -> 5571.105 | O21: =E4*F22 -> 26585.322 | P21: =F4*G22 -> 2320.7625 | Q21: =X21*H22 -> 11425.32 | R21: =I22*Y21 -> 16925.76 | S21: =(SUM(M21:R21))*0.02 -> 1272.1188 | T21: =((M4/100)*(SUM(M21:S21)))*(-1) -> -1531.1222 | U21: =SUM(M21:T21) -> 63346.937 | V21: =U21*1.16 -> 73482.446 | X21: =IF(L4<=J4,L4,J4) -> 54 | Y21: =IF(L4<=K4,L4,K4) -> 54
C22: ENERO | D22: 777.67 | E22: 1.0275 | F22: 1.6562 | G22: 1.8375 | H22: 211.58 | I22: 313.44 | L22: FEBRERO | M22: =D23 -> 777.67 | N22: =D5*E23 -> 5438.5575 | O22: =E5*F23 -> 25949.342 | P22: =F5*G23 -> 2265.6375 | Q22: =X22*H23 -> 12271.64 | R22: =I23*Y22 -> 18179.52 | S22: =(SUM(M22:R22))*0.02 -> 1297.6473 | T22: =((M5/100)*(SUM(M22:S22)))*(-1) -> -1548.6123 | U22: =SUM(M22:T22) -> 64631.402 | V22: =U22*1.16 -> 74972.426 | X22: =IF(L5<=J5,L5,J5) -> 58 | Y22: =IF(L5<=K5,L5,K5) -> 58
C23: FEBRERO | D23: 777.67 | E23: 1.0275 | F23: 1.6562 | G23: 1.8375 | H23: 211.58 | I23: 313.44 | L23: MARZO | M23: =D24 -> 777.67 | N23: =D6*E24 -> 6356.115 | O23: =E6*F24 -> 30326.678 | P23: =F6*G24 -> 2647.8375 | Q23: =X23*H24 -> 13117.96 | R23: =I24*Y23 -> 19433.28 | S23: =(SUM(M23:R23))*0.02 -> 1453.1908 | T23: =((M6/100)*(SUM(M23:S23)))*(-1) -> -1667.5365 | U23: =SUM(M23:T23) -> 72445.195 | V23: =U23*1.16 -> 84036.426 | X23: =IF(L6<=J6,L6,J6) -> 62 | Y23: =IF(L6<=K6,L6,K6) -> 62
C24: MARZO | D24: 777.67 | E24: 1.0275 | F24: 1.6562 | G24: 1.8375 | H24: 211.58 | I24: 313.44 | L24: ABRIL | M24: =D25 -> 777.67 | N24: =D7*E25 -> 7245.93 | O24: =E7*F25 -> 34573.175 | P24: =F7*G25 -> 3019.0125 | Q24: =X24*H25 -> 15445.34 | R24: =I25*Y24 -> 22881.12 | S24: =(SUM(M24:R24))*0.02 -> 1678.8449 | T24: =((M7/100)*(SUM(M24:S24)))*(-1) -> -1849.4156 | U24: =SUM(M24:T24) -> 83771.677 | V24: =U24*1.16 -> 97175.145 | X24: =IF(L7<=J7,L7,J7) -> 73 | Y24: =IF(L7<=K7,L7,K7) -> 73
C25: ABRIL | D25: 777.67 | E25: 1.0275 | F25: 1.6562 | G25: 1.8375 | H25: 211.58 | I25: 313.44 | L25: MAYO | M25: =D26 -> 777.67 | N25: =D8*E26 -> 9111.87 | O25: =E8*F26 -> 43478.562 | P25: =F8*G26 -> 3796.275 | Q25: =X25*H26 -> 18619.04 | R25: =I26*Y25 -> 27582.72 | S25: =(SUM(M25:R25))*0.02 -> 2067.3227 | T25: =((M8/100)*(SUM(M25:S25)))*(-1) -> -2171.9293 | U25: =SUM(M25:T25) -> 103261.53 | V25: =U25*1.16 -> 119783.38 | X25: =IF(L8<=J8,L8,J8) -> 88 | Y25: =IF(L8<=K8,L8,K8) -> 88
C26: MAYO | D26: 777.67 | E26: 1.0275 | F26: 1.6562 | G26: 1.8375 | H26: 211.58 | I26: 313.44 | L26: JUNIO | M26: =D27 -> 777.67 | N26: =D9*E27 -> 10217.46 | O26: =E9*F27 -> 48753.559 | P26: =F9*G27 -> 4255.65 | Q26: =X26*H27 -> 21581.16 | R26: =I27*Y26 -> 31970.88 | S26: =(SUM(M26:R26))*0.02 -> 2351.1276 | T26: =((M9/100)*(SUM(M26:S26)))*(-1) -> -2326.2056 | U26: =SUM(M26:T26) -> 117581.3 | V26: =U26*1.16 -> 136394.31 | X26: =IF(L9<=J9,L9,J9) -> 102 | Y26: =IF(L9<=K9,L9,K9) -> 102
C27: JUNIO | D27: 777.67 | E27: 1.0275 | F27: 1.6562 | G27: 1.8375 | H27: 211.58 | I27: 313.44 | L27: JULIO | M27: =D28 -> 777.67 | N27: =D10*E28 -> 10801.08 | O27: =E10*F28 -> 51540.944 | P27: =F10*G28 -> 4498.2 | Q27: =X27*H28 -> 22004.32 | R27: =I28*Y27 -> 24134.88 | S27: =(SUM(M27:R27))*0.02 -> 2275.1419 | T27: =((M10/100)*(SUM(M27:S27)))*(-1) -> -2193.0093 | U27: =SUM(M27:T27) -> 113839.23 | V27: =U27*1.16 -> 132053.5 | X27: =IF(L10<=J10,L10,J10) -> 104 | Y27: =IF(L10<=K10,L10,K10) -> 77
C28: JULIO | D28: 777.67 | E28: 1.0275 | F28: 1.6562 | G28: 1.8375 | H28: 211.58 | I28: 313.44 | L28: AGOSTO | M28: =D29 -> 777.67 | N28: =D11*E29 -> 11159.678 | O28: =E11*F29 -> 53251.799 | P28: =F11*G29 -> 4648.875 | Q28: =X28*H29 -> 22850.64 | R28: =I29*Y28 -> 33851.52 | S28: =(SUM(M28:R28))*0.02 -> 2530.8036 | T28: =((M11/100)*(SUM(M28:S28)))*(-1) -> -2581.4197 | U28: =SUM(M28:T28) -> 126489.57 | V28: =U28*1.16 -> 146727.9 | X28: =IF(L11<=J11,L11,J11) -> 108 | Y28: =IF(L11<=K11,L11,K11) -> 108
C29: AGOSTO | D29: 777.67 | E29: 1.0275 | F29: 1.6562 | G29: 1.8375 | H29: 211.58 | I29: 313.44 | L29: SEPTIEMBRE | M29: =D30 -> 777.67 | N29: =D12*E30 -> 10794.915 | O29: =E12*F30 -> 51509.476 | P29: =F12*G30 -> 4496.3625 | Q29: =X29*H30 -> 22850.64 | R29: =I30*Y29 -> 33851.52 | S29: =(SUM(M29:R29))*0.02 -> 2485.6117 | T29: =((M12/100)*(SUM(M29:S29)))*(-1) -> -2548.0005 | U29: =SUM(M29:T29) -> 124218.19 | V29: =U29*1.16 -> 144093.11 | X29: =IF(L12<=J12,L12,J12) -> 108 | Y29: =IF(L12<=K12,L12,K12) -> 108
C30: SEPTIEMBRE | D30: 777.67 | E30: 1.0275 | F30: 1.6562 | G30: 1.8375 | H30: 211.58 | I30: 313.44 | L30: OCTUBRE | M30: =D31 -> 777.67 | N30: =D13*E31 -> 11030.213 | O30: =E13*F31 -> 52635.692 | P30: =F13*G31 -> 4593.75 | Q30: =X30*H31 -> 22639.06 | R30: =I31*Y30 -> 33538.08 | S30: =(SUM(M30:R30))*0.02 -> 2504.2893 | T30: =((M13/100)*(SUM(M30:S30)))*(-1) -> -2618.2345 | U30: =SUM(M30:T30) -> 125100.52 | V30: =U30*1.16 -> 145116.6 | X30: =IF(L13<=J13,L13,J13) -> 107 | Y30: =IF(L13<=K13,L13,K13) -> 107
C31: OCTUBRE | D31: 777.67 | E31: 1.0275 | F31: 1.6562 | G31: 1.8375 | H31: 211.58 | I31: 313.44 | L31: NOVIEMBRE | M31: =D32 -> 777.67 | N31: =D14*E32 -> 8291.925 | O31: =E14*F32 -> 39566.618 | P31: =F14*G32 -> 3454.5 | Q31: =X31*H32 -> 17561.14 | R31: =I32*Y31 -> 26015.52 | S31: =(SUM(M31:R31))*0.02 -> 1913.3475 | T31: =((M14/100)*(SUM(M31:S31)))*(-1) -> -2156.5339 | U31: =SUM(M31:T31) -> 95424.187 | V31: =U31*1.16 -> 110692.06 | X31: =IF(L14<=J14,L14,J14) -> 83 | Y31: =IF(L14<=K14,L14,K14) -> 83
C32: NOVIEMBRE | D32: 777.67 | E32: 1.0275 | F32: 1.6562 | G32: 1.8375 | H32: 211.58 | I32: 313.44 | L32: DICIEMBRE | M32: =D33 -> 777.67 | N32: =D15*E33 -> 7507.9425 | O32: =E15*F33 -> 35826.918 | P32: =F15*G33 -> 3127.425 | Q32: =X32*H33 -> 15445.34 | R32: =I33*Y32 -> 22881.12 | S32: =(SUM(M32:R32))*0.02 -> 1711.3283 | T32: =((M15/100)*(SUM(M32:S32)))*(-1) -> -1815.3771 | U32: =SUM(M32:T32) -> 85462.367 | V32: =U32*1.16 -> 99136.346 | X32: =IF(L15<=J15,L15,J15) -> 73 | Y32: =IF(L15<=K15,L15,K15) -> 73
C33: DICIEMBRE | D33: 777.67 | E33: 1.0275 | F33: 1.6562 | G33: 1.8375 | H33: 211.58 | I33: 313.44 | U33: =SUM(U21:U32) -> 1175572.1 | V33: =U33*1.16 -> 1363663.6
N35: CON FOTOVOLTAICO
M36: FIJO ($) | N36: ENERGÍA BASE ($/KWH) | O36: ENERGÍA INTERMEDIO ($/KWH) | P36: ENERGÍA PUNTA ($/KWH) | Q36: DISTRIBUCIÓN ($/KW) | R36: CAPACIDAD ($/KW) | S36: CARGO POR BAJA TENSIÓN (2%) | T36: CARGO FACTOR DE POTENCIA | U36: TOTAL | V36: TOTAL + IVA | X36: MULTIPLICADORES
L37: ENERO | M37: =M21 -> 777.67 | N37: =U4*E22 -> 0 | O37: =V4*F22 -> 0 | P37: =W4*G22 -> 0 | Q37: =X38*H22 -> 0 | R37: =I22*Y38 -> 0 | S37: =(SUM(M37:R37))*0.02 -> 15.5534 | T37: =((Z4/100)*SUM(M37:S37))*(-1) -> -19.830585 | U37: =SUM(M37:T37) -> 773.39281 | V37: =U37*1.16 -> 897.13567 | X37: DISTRIBUCIÓN | Y37: CAPACIDAD
L38: FEBRERO | M38: =M22 -> 777.67 | N38: =U5*E23 -> 0 | O38: =V5*F23 -> 0 | P38: =W5*G23 -> 0 | Q38: =X39*H23 -> 0 | R38: =I23*Y39 -> 0 | S38: =(SUM(M38:R38))*0.02 -> 15.5534 | T38: =((Z5/100)*SUM(M38:S38))*(-1) -> -19.830585 | U38: =SUM(M38:T38) -> 773.39281 | V38: =U38*1.16 -> 897.13567 | X38: =IF(AC4<=AA4,AC4,AA4) -> 0 | Y38: =IF(AC4<=AB4,AC4,AB4) -> 0
L39: MARZO | M39: =M23 -> 777.67 | N39: =U6*E24 -> 0 | O39: =V6*F24 -> 0 | P39: =W6*G24 -> 0 | Q39: =X40*H24 -> 0 | R39: =I24*Y40 -> 0 | S39: =(SUM(M39:R39))*0.02 -> 15.5534 | T39: =((Z6/100)*SUM(M39:S39))*(-1) -> -19.830585 | U39: =SUM(M39:T39) -> 773.39281 | V39: =U39*1.16 -> 897.13567 | X39: =IF(AC5<=AA5,AC5,AA5) -> 0 | Y39: =IF(AC5<=AB5,AC5,AB5) -> 0
L40: ABRIL | M40: =M24 -> 777.67 | N40: =U7*E25 -> 0 | O40: =V7*F25 -> 0 | P40: =W7*G25 -> 0 | Q40: =X41*H25 -> 0 | R40: =I25*Y41 -> 0 | S40: =(SUM(M40:R40))*0.02 -> 15.5534 | T40: =((Z7/100)*SUM(M40:S40))*(-1) -> -19.830585 | U40: =SUM(M40:T40) -> 773.39281 | V40: =U40*1.16 -> 897.13567 | X40: =IF(AC6<=AA6,AC6,AA6) -> 0 | Y40: =IF(AC6<=AB6,AC6,AB6) -> 0
L41: MAYO | M41: =M25 -> 777.67 | N41: =U8*E26 -> 0 | O41: =V8*F26 -> 0 | P41: =W8*G26 -> 0 | Q41: =X42*H26 -> 0 | R41: =I26*Y42 -> 0 | S41: =(SUM(M41:R41))*0.02 -> 15.5534 | T41: =((Z8/100)*SUM(M41:S41))*(-1) -> -19.830585 | U41: =SUM(M41:T41) -> 773.39281 | V41: =U41*1.16 -> 897.13567 | X41: =IF(AC7<=AA7,AC7,AA7) -> 0 | Y41: =IF(AC7<=AB7,AC7,AB7) -> 0
L42: JUNIO | M42: =M26 -> 777.67 | N42: =U9*E27 -> 0 | O42: =V9*F27 -> 0 | P42: =W9*G27 -> 0 | Q42: =X43*H27 -> 0 | R42: =I27*Y43 -> 0 | S42: =(SUM(M42:R42))*0.02 -> 15.5534 | T42: =((Z9/100)*SUM(M42:S42))*(-1) -> -19.830585 | U42: =SUM(M42:T42) -> 773.39281 | V42: =U42*1.16 -> 897.13567 | X42: =IF(AC8<=AA8,AC8,AA8) -> 0 | Y42: =IF(AC8<=AB8,AC8,AB8) -> 0
L43: JULIO | M43: =M27 -> 777.67 | N43: =U10*E28 -> 0 | O43: =V10*F28 -> 0 | P43: =W10*G28 -> 0 | Q43: =X44*H28 -> 0 | R43: =I28*Y44 -> 0 | S43: =(SUM(M43:R43))*0.02 -> 15.5534 | T43: =((Z10/100)*SUM(M43:S43))*(-1) -> -19.830585 | U43: =SUM(M43:T43) -> 773.39281 | V43: =U43*1.16 -> 897.13567 | X43: =IF(AC9<=AA9,AC9,AA9) -> 0 | Y43: =IF(AC9<=AB9,AC9,AB9) -> 0
L44: AGOSTO | M44: =M28 -> 777.67 | N44: =U11*E29 -> 0 | O44: =V11*F29 -> 0 | P44: =W11*G29 -> 0 | Q44: =X45*H29 -> 0 | R44: =I29*Y45 -> 0 | S44: =(SUM(M44:R44))*0.02 -> 15.5534 | T44: =((Z11/100)*SUM(M44:S44))*(-1) -> -19.830585 | U44: =SUM(M44:T44) -> 773.39281 | V44: =U44*1.16 -> 897.13567 | X44: =IF(AC10<=AA10,AC10,AA10) -> 0 | Y44: =IF(AC10<=AB10,AC10,AB10) -> 0
L45: SEPTIEMBRE | M45: =M29 -> 777.67 | N45: =U12*E30 -> 0 | O45: =V12*F30 -> 0 | P45: =W12*G30 -> 0 | Q45: =X46*H30 -> 0 | R45: =I30*Y46 -> 0 | S45: =(SUM(M45:R45))*0.02 -> 15.5534 | T45: =((Z12/100)*SUM(M45:S45))*(-1) -> -19.830585 | U45: =SUM(M45:T45) -> 773.39281 | V45: =U45*1.16 -> 897.13567 | X45: =IF(AC11<=AA11,AC11,AA11) -> 0 | Y45: =IF(AC11<=AB11,AC11,AB11) -> 0
L46: OCTUBRE | M46: =M30 -> 777.67 | N46: =U13*E31 -> 0 | O46: =V13*F31 -> 0 | P46: =W13*G31 -> 0 | Q46: =X47*H31 -> 0 | R46: =I31*Y47 -> 0 | S46: =(SUM(M46:R46))*0.02 -> 15.5534 | T46: =((Z13/100)*SUM(M46:S46))*(-1) -> -19.830585 | U46: =SUM(M46:T46) -> 773.39281 | V46: =U46*1.16 -> 897.13567 | X46: =IF(AC12<=AA12,AC12,AA12) -> 0 | Y46: =IF(AC12<=AB12,AC12,AB12) -> 0
L47: NOVIEMBRE | M47: =M31 -> 777.67 | N47: =U14*E32 -> 0 | O47: =V14*F32 -> 0 | P47: =W14*G32 -> 0 | Q47: =X48*H32 -> 0 | R47: =I32*Y48 -> 0 | S47: =(SUM(M47:R47))*0.02 -> 15.5534 | T47: =((Z14/100)*SUM(M47:S47))*(-1) -> -19.830585 | U47: =SUM(M47:T47) -> 773.39281 | V47: =U47*1.16 -> 897.13567 | X47: =IF(AC13<=AA13,AC13,AA13) -> 0 | Y47: =IF(AC13<=AB13,AC13,AB13) -> 0
L48: DICIEMBRE | M48: =M32 -> 777.67 | N48: =U15*E33 -> 0 | O48: =V15*F33 -> 0 | P48: =W15*G33 -> 0 | Q48: =X49*H33 -> 0 | R48: =I33*Y49 -> 0 | S48: =(SUM(M48:R48))*0.02 -> 15.5534 | T48: =((Z15/100)*SUM(M48:S48))*(-1) -> -19.830585 | U48: =SUM(M48:T48) -> 773.39281 | V48: =U48*1.16 -> 897.13567 | X48: =IF(AC14<=AA14,AC14,AA14) -> 0 | Y48: =IF(AC14<=AB14,AC14,AB14) -> 0
T49: =SUM(T37:T48) -> -237.96702 | U49: =SUM(U37:U48) -> 9280.7138 | V49: =U49*1.16 -> 10765.628 | X49: =IF(AC15<=AA15,AC15,AA15) -> 0 | Y49: =IF(AC15<=AB15,AC15,AB15) -> 0
V50: =V33-V49 -> 1352898
V52: =V50/2 -> 676449.01
M53: Contraprestación: No modificar | V53: 676449.01
J54: Balance | L54: A favor | M54: En contra | N54: Restante | O54: Restante final | Q54: Consumo final
I55: Enero | J55: =G4-S4 -> -10244 | K55: =IF(J55<0,J55,0) -> -10244 | L55: =K55*-1 -> 10244 | M55: =IF(J55<=0,0,J55) -> 0 | N55: =L67 -> 55861 | O55: =IF(N55>0,N55,0) -> 55861 | P55: =IF(N56>0,0,M55) -> 0 | Q55: =IF(N55>M55,0,M55-O55) -> 0
I56: Febrero | J56: =G5-S5 -> -11684 | K56: =IF(J56<0,J56,0) -> -11684 | L56: =K56*-1 -> 11684 | M56: =IF(J56<=0,0,J56) -> 0 | N56: =L67-M55 -> 55861 | O56: =IF(N56>0,N56,0) -> 55861 | P56: =IF(N57>0,0,M56) -> 0 | Q56: =IF(N56>M56,0,M56-O56) -> 0
I57: Marzo | J57: =G6-S6 -> -15839 | K57: =IF(J57<0,J57,0) -> -15839 | L57: =K57*-1 -> 15839 | M57: =IF(J57<=0,0,J57) -> 0 | N57: =N56-M56 -> 55861 | O57: =IF(N57>0,N57,0) -> 55861 | P57: =IF(N58>0,0,M57) -> 0 | Q57: =IF(N57>M57,0,M57-O57) -> 0
I58: Abril | J58: =G7-S7 -> -11617 | K58: =IF(J58<0,J58,0) -> -11617 | L58: =K58*-1 -> 11617 | M58: =IF(J58<=0,0,J58) -> 0 | N58: =N57-M57 -> 55861 | O58: =IF(N58>0,N58,0) -> 55861 | P58: =IF(N59>0,0,M58) -> 0 | Q58: =IF(N58>M58,0,M58-O58) -> 0
I59: Mayo | J59: =G8-S8 -> -3898 | K59: =IF(J59<0,J59,0) -> -3898 | L59: =K59*-1 -> 3898 | M59: =IF(J59<=0,0,J59) -> 0 | N59: =N58-M58 -> 55861 | O59: =IF(N59>0,N59,0) -> 55861 | P59: =IF(N60>0,0,M59) -> 0 | Q59: =IF(N59>M59,0,M59-O59) -> 0
I60: Junio | J60: =G9-S9 -> 7210 | K60: =IF(J60<0,J60,0) -> 0 | L60: =K60*-1 -> 0 | M60: =IF(J60<=0,0,J60) -> 7210 | N60: =N59-M59 -> 55861 | O60: =IF(N60>0,N60,0) -> 55861 | P60: =IF(N61>0,0,M60) -> 0 | Q60: =IF(N60>M60,0,M60-O60) -> 0
I61: Julio | J61: =G10-S10 -> 11839 | K61: =IF(J61<0,J61,0) -> 0 | L61: =K61*-1 -> 0 | M61: =IF(J61<=0,0,J61) -> 11839 | N61: =N60-M60 -> 48651 | O61: =IF(N61>0,N61,0) -> 48651 | P61: =IF(N62>0,0,M61) -> 0 | Q61: =IF(N61>M61,0,M61-O61) -> 0
I62: Agosto | J62: =G11-S11 -> 12881 | K62: =IF(J62<0,J62,0) -> 0 | L62: =K62*-1 -> 0 | M62: =IF(J62<=0,0,J62) -> 12881 | N62: =N61-M61 -> 36812 | O62: =IF(N62>0,N62,0) -> 36812 | P62: =IF(N63>0,0,M62) -> 0 | Q62: =IF(N62>M62,0,M62-O62) -> 0
I63: Septiembre | J63: =G12-S12 -> 13083 | K63: =IF(J63<0,J63,0) -> 0 | L63: =K63*-1 -> 0 | M63: =IF(J63<=0,0,J63) -> 13083 | N63: =N62-M62 -> 23931 | O63: =IF(N63>0,N63,0) -> 23931 | P63: =IF(N64>0,0,M63) -> 0 | Q63: =IF(N63>M63,0,M63-O63) -> 0
I64: Octubre | J64: =G13-S13 -> 8252 | K64: =IF(J64<0,J64,0) -> 0 | L64: =K64*-1 -> 0 | M64: =IF(J64<=0,0,J64) -> 8252 | N64: =N63-M63 -> 10848 | O64: =IF(N64>0,N64,0) -> 10848 | P64: =IF(N65>0,0,M64) -> 0 | Q64: =IF(N64>M64,0,M64-O64) -> 0
I65: Noviembre | J65: =G14-S14 -> -844 | K65: =IF(J65<0,J65,0) -> -844 | L65: =K65*-1 -> 844 | M65: =IF(J65<=0,0,J65) -> 0 | N65: =N64-M64 -> 2596 | O65: =IF(N65>0,N65,0) -> 2596 | P65: =IF(N66>0,0,M65) -> 0 | Q65: =IF(N65>M65,0,M65-O65) -> 0
I66: Diciembre | J66: =G15-S15 -> -1735 | K66: =IF(J66<0,J66,0) -> -1735 | L66: =K66*-1 -> 1735 | M66: =IF(J66<=0,0,J66) -> 0 | N66: =N65-M65 -> 2596 | O66: =IF(N66>0,N66,0) -> 2596 | P66: =IF(N67>0,0,M66) -> 0 | Q66: =IF(N66>M66,0,M66-O66) -> 0
L67: =SUM(L55:L66) -> 55861 | N67: =N66-M66 -> 2596 | O67: =IF(N67>0,N67,0) -> 2596 | Q67: =SUM(Q55:Q66) -> 0
J70: Energía generada en intermedio | K70: Consumo intermedio | L70: Consumo resultante | M70: Abonado | N70: Energía a pagar en intermedio
I71: Enero | J71: =S4 -> 32981 | K71: =E4 -> 16052 | L71: =K71-J71 -> -16929 | M71: =IF(L71<0,L71,0) -> -16929 | N71: =IF(L71>0,L71,0) -> 0
H72: =SUM(J71:J82) -> 425093 | I72: Febrero | J72: =S5 -> 33878 | K72: =E5 -> 15668 | L72: =K72-J72 -> -18210 | M72: =IF(L72<0,L72,0) -> -18210 | N72: =IF(L72>0,L72,0) -> 0
I73: Marzo | J73: =S6 -> 41777 | K73: =E6 -> 18311 | L73: =K73-J73 -> -23466 | M73: =IF(L73<0,L73,0) -> -23466 | N73: =IF(L73>0,L73,0) -> 0
I74: Abril | J74: =S7 -> 41187 | K74: =E7 -> 20875 | L74: =K74-J74 -> -20312 | M74: =IF(L74<0,L74,0) -> -20312 | N74: =IF(L74>0,L74,0) -> 0
I75: Mayo | J75: =S8 -> 41084 | K75: =E8 -> 26252 | L75: =K75-J75 -> -14832 | M75: =IF(L75<0,L75,0) -> -14832 | N75: =IF(L75>0,L75,0) -> 0
I76: Junio | J76: =S9 -> 34487 | K76: =E9 -> 29437 | L76: =K76-J76 -> -5050 | M76: =IF(L76<0,L76,0) -> -5050 | N76: =IF(L76>0,L76,0) -> 0
I77: Julio | J77: =S10 -> 32241 | K77: =E10 -> 31120 | L77: =K77-J77 -> -1121 | M77: =IF(L77<0,L77,0) -> -1121 | N77: =IF(L77>0,L77,0) -> 0
I78: Agosto | J78: =S11 -> 32663 | K78: =E11 -> 32153 | L78: =K78-J78 -> -510 | M78: =IF(L78<0,L78,0) -> -510 | N78: =IF(L78>0,L78,0) -> 0
A79: =ACOS(H4/100) -> 0.1114129 | B79: =A79*(180/3.1416) -> 6.3834741 | I79: Septiembre | J79: =S12 -> 30971 | K79: =E12 -> 31101 | L79: =K79-J79 -> 130 | M79: =IF(L79<0,L79,0) -> 0 | N79: =IF(L79>0,L79,0) -> 130
A80: =ACOS(H5/100) -> 0.11923437 | B80: =A80*(180/3.1416) -> 6.8316103 | I80: Octubre | J80: =S13 -> 36764 | K80: =E13 -> 31781 | L80: =K80-J80 -> -4983 | M80: =IF(L80<0,L80,0) -> -4983 | N80: =IF(L80>0,L80,0) -> 0
A81: =ACOS(H6/100) -> 0.15047489 | B81: =A81*(180/3.1416) -> 8.6215559 | I81: Noviembre | J81: =S14 -> 34684 | K81: =E14 -> 23890 | L81: =K81-J81 -> -10794 | M81: =IF(L81<0,L81,0) -> -10794 | N81: =IF(L81>0,L81,0) -> 0
A82: =ACOS(H7/100) -> 0.17342232 | B82: =A82*(180/3.1416) -> 9.9363438 | I82: Diciembre | J82: =S15 -> 32376 | K82: =E15 -> 21632 | L82: =K82-J82 -> -10744 | M82: =IF(L82<0,L82,0) -> -10744 | N82: =IF(L82>0,L82,0) -> 0
A83: =ACOS(H8/100) -> 0.197297 | B83: =A83*(180/3.1416) -> 11.304259
A84: =ACOS(H9/100) -> 0.22090295 | B84: =A84*(180/3.1416) -> 12.656777
A85: =ACOS(H10/100) -> 0.23116561 | B85: =A85*(180/3.1416) -> 13.244783 | I85: Compensación intermedio a punta | J85: Energía consumida en intermedio | K85: Energía abonada en intermedio | L85: Energía a pagar en punta | M85: Conversión de intermedio a punta | N85: Compensación de intermedio a punta ( Saldo final punta) | O85: Saldo restante después de contraprestación | P85: Saldo disponible mes tras mes
A86: =ACOS(H11/100) -> 0.21062709 | B86: =A86*(180/3.1416) -> 12.068015 | I86: Enero | J86: =N71 -> 0 | K86: =M71*-1 -> 16929 | L86: =F4 -> 1263 | M86: =ROUNDDOWN((F22/G22)*K86,0) -> 15258 | N86: =IF(O86>=0,0,O86*-1) -> 0 | O86: =P86-L86 -> 113155 | P86: =M98 -> 114418
A87: =ACOS(H12/100) -> 0.20870524 | B87: =A87*(180/3.1416) -> 11.957902 | I87: Febrero | J87: =N72 -> 0 | K87: =M72*-1 -> 18210 | L87: =F5 -> 1233 | M87: =ROUNDDOWN((F23/G23)*K87,0) -> 16413 | N87: =IF(O87>=0,0,O87*-1) -> 0 | O87: =P87-L87 -> 111922 | P87: =IF(O86>0,O86*1,0) -> 113155
A88: =ACOS(H13/100) -> 0.20033484 | B88: =A88*(180/3.1416) -> 11.478314 | I88: Marzo | J88: =N73 -> 0 | K88: =M73*-1 -> 23466 | L88: =F6 -> 1441 | M88: =ROUNDDOWN((F24/G24)*K88,0) -> 21150 | N88: =IF(O88>=0,0,O88*-1) -> 0 | O88: =P88-L88 -> 110481 | P88: =IF(O87>0,O87*1,0) -> 111922
A89: =ACOS(H14/100) -> 0.16079696 | B89: =A89*(180/3.1416) -> 9.2129655 | I89: Abril | J89: =N74 -> 0 | K89: =M74*-1 -> 20312 | L89: =F7 -> 1643 | M89: =ROUNDDOWN((F25/G25)*K89,0) -> 18307 | N89: =IF(O89>=0,0,O89*-1) -> 0 | O89: =P89-L89 -> 108838 | P89: =IF(O88>0,O88*1,0) -> 110481
A90: =ACOS(H15/100) -> 0.19212863 | B90: =A90*(180/3.1416) -> 11.008134 | I90: Mayo | J90: =N75 -> 0 | K90: =M75*-1 -> 14832 | L90: =F8 -> 2066 | M90: =ROUNDDOWN((F26/G26)*K90,0) -> 13368 | N90: =IF(O90>=0,0,O90*-1) -> 0 | O90: =P90-L90 -> 106772 | P90: =IF(O89>0,O89*1,0) -> 108838
I91: Junio | J91: =N76 -> 0 | K91: =M76*-1 -> 5050 | L91: =F9 -> 2316 | M91: =ROUNDDOWN((F27/G27)*K91,0) -> 4551 | N91: =IF(O91>=0,0,O91*-1) -> 0 | O91: =P91-L91 -> 104456 | P91: =IF(O90>0,O90*1,0) -> 106772
I92: Julio | J92: =N77 -> 0 | K92: =M77*-1 -> 1121 | L92: =F10 -> 2448 | M92: =ROUNDDOWN((F28/G28)*K92,0) -> 1010 | N92: =IF(O92>=0,0,O92*-1) -> 0 | O92: =P92-L92 -> 102008 | P92: =IF(O91>0,O91*1,0) -> 104456
I93: Agosto | J93: =N78 -> 0 | K93: =M78*-1 -> 510 | L93: =F11 -> 2530 | M93: =ROUNDDOWN((F29/G29)*K93,0) -> 459 | N93: =IF(O93>=0,0,O93*-1) -> 0 | O93: =P93-L93 -> 99478 | P93: =IF(O92>0,O92*1,0) -> 102008
I94: Septiembre | J94: =N79 -> 130 | K94: =M79*-1 -> 0 | L94: =F12 -> 2447 | M94: =ROUNDDOWN((F30/G30)*K94,0) -> 0 | N94: =IF(O94>=0,0,O94*-1) -> 0 | O94: =P94-L94 -> 97031 | P94: =IF(O93>0,O93*1,0) -> 99478
I95: Octubre | J95: =N80 -> 0 | K95: =M80*-1 -> 4983 | L95: =F13 -> 2500 | M95: =ROUNDDOWN((F31/G31)*K95,0) -> 4491 | N95: =IF(O95>=0,0,O95*-1) -> 0 | O95: =P95-L95 -> 94531 | P95: =IF(O94>0,O94*1,0) -> 97031
A96: =SIN(A79)*$I$4 -> 2543.7456 | I96: Noviembre | J96: =N81 -> 0 | K96: =M81*-1 -> 10794 | L96: =F14 -> 1880 | M96: =ROUNDDOWN((F32/G32)*K96,0) -> 9728 | N96: =IF(O96>=0,0,O96*-1) -> 0 | O96: =P96-L96 -> 92651 | P96: =IF(O95>0,O95*1,0) -> 94531
A97: =SIN(A80)*$I$4 -> 2721.5039 | I97: Diciembre | J97: =N82 -> 0 | K97: =M82*-1 -> 10744 | L97: =F15 -> 1702 | M97: =ROUNDDOWN((F33/G33)*K97,0) -> 9683 | N97: =IF(O97>=0,0,O97*-1) -> 0 | O97: =P97-L97 -> 90949 | P97: =IF(O96>0,O96*1,0) -> 92651
A98: =SIN(A81)*$I$4 -> 3429.7376 | K98: =SUM(K86:K97) -> 126951 | M98: =SUM(M86:M97) -> 114418 | N98: =IF(O98>=0,0,O98*-1) -> 0
A99: =SIN(A82)*$I$4 -> 3947.8707
A100: =SIN(A83)*$I$4 -> 4484.7299
A101: =SIN(A84)*$I$4 -> 5013.0343 | I101: Compensación intermedio a intermedio | J101: Energía consumida en intermedio | K101: Conversión de intermedio a intermedio | L101: Compensación de intermedio a intermedio (saldo final intermedio) | M101: Saldo restante después de contraprestación | N101: Saldo disponible mes tras mes
A102: =SIN(A85)*$I$4 -> 5241.86 | I102: Enero | J102: =J86 -> 0 | K102: =J102 -> 0 | L102: =IF(M102>=0,0,M102*-1) -> 0 | M102: =N102-J102 -> 100905 | N102: =ROUNDUP(IF(O97>0,(O97*(G22/F22)),0),0) -> 100905
A103: =SIN(A86)*$I$4 -> 4783.385 | I103: Febrero | J103: =J87 -> 0 | K103: =J103 -> 0 | L103: =IF(M103>=0,0,M103*-1) -> 0 | M103: =N103-J103 -> 100905 | N103: =IF(M102>0,M102*1,0) -> 100905
A104: =SIN(A87)*$I$4 -> 4740.3781 | I104: Marzo | J104: =J88 -> 0 | K104: =J104 -> 0 | L104: =IF(M104>=0,0,M104*-1) -> 0 | M104: =N104-J104 -> 100905 | N104: =IF(M103>0,M103*1,0) -> 100905
A105: =SIN(A88)*$I$4 -> 4552.8635 | I105: Abril | J105: =J89 -> 0 | K105: =J105 -> 0 | L105: =IF(M105>=0,0,M105*-1) -> 0 | M105: =N105-J105 -> 100905 | N105: =IF(M104>0,M104*1,0) -> 100905
A106: =SIN(A89)*$I$4 -> 3663.0408 | I106: Mayo | J106: =J90 -> 0 | K106: =J106 -> 0 | L106: =IF(M106>=0,0,M106*-1) -> 0 | M106: =N106-J106 -> 100905 | N106: =IF(M105>0,M105*1,0) -> 100905
...

Sheet tabla general
F5: Mes | G5: Consumo histórico (kWh) | H5: Energía generada por el sistema (kWh) | I5: Pago histórico ($) | J5: Pago nuevo ($) | K5: Ahorro por periodo ($)
F6: Enero | G6: ='CON FACTOR DE POTENCIA '!G4 -> 22737 | H6: ='CON FACTOR DE POTENCIA '!S4 -> 32981 | I6: ='CON FACTOR DE POTENCIA '!V21 -> 73482.446 | J6: ='CON FACTOR DE POTENCIA '!V37 -> 897.13567 | K6: =I6-J6 -> 72585.311
F7: Febrero | G7: ='CON FACTOR DE POTENCIA '!G5 -> 22194 | H7: ='CON FACTOR DE POTENCIA '!S5 -> 33878 | I7: ='CON FACTOR DE POTENCIA '!V22 -> 74972.426 | J7: ='CON FACTOR DE POTENCIA '!V38 -> 897.13567 | K7: =I7-J7 -> 74075.29
F8: Marzo | G8: ='CON FACTOR DE POTENCIA '!G6 -> 25938 | H8: ='CON FACTOR DE POTENCIA '!S6 -> 41777 | I8: ='CON FACTOR DE POTENCIA '!V23 -> 84036.426 | J8: ='CON FACTOR DE POTENCIA '!V39 -> 897.13567 | K8: =I8-J8 -> 83139.291
F9: Abril | G9: ='CON FACTOR DE POTENCIA '!G7 -> 29570 | H9: ='CON FACTOR DE POTENCIA '!S7 -> 41187 | I9: ='CON FACTOR DE POTENCIA '!V24 -> 97175.145 | J9: ='CON FACTOR DE POTENCIA '!V40 -> 897.13567 | K9: =I9-J9 -> 96278.009
F10: Mayo | G10: ='CON FACTOR DE POTENCIA '!G8 -> 37186 | H10: ='CON FACTOR DE POTENCIA '!S8 -> 41084 | I10: ='CON FACTOR DE POTENCIA '!V25 -> 119783.38 | J10: ='CON FACTOR DE POTENCIA '!V41 -> 897.13567 | K10: =I10-J10 -> 118886.24
F11: Junio | G11: ='CON FACTOR DE POTENCIA '!G9 -> 41697 | H11: ='CON FACTOR DE POTENCIA '!S9 -> 34487 | I11: ='CON FACTOR DE POTENCIA '!V26 -> 136394.31 | J11: ='CON FACTOR DE POTENCIA '!V42 -> 897.13567 | K11: =I11-J11 -> 135497.17
F12: Julio | G12: ='CON FACTOR DE POTENCIA '!G10 -> 44080 | H12: ='CON FACTOR DE POTENCIA '!S10 -> 32241 | I12: ='CON FACTOR DE POTENCIA '!V27 -> 132053.5 | J12: ='CON FACTOR DE POTENCIA '!V43 -> 897.13567 | K12: =I12-J12 -> 131156.37
F13: Agosto | G13: ='CON FACTOR DE POTENCIA '!G11 -> 45544 | H13: ='CON FACTOR DE POTENCIA '!S11 -> 32663 | I13: ='CON FACTOR DE POTENCIA '!V28 -> 146727.9 | J13: ='CON FACTOR DE POTENCIA '!V44 -> 897.13567 | K13: =I13-J13 -> 145830.76
F14: Septiembre | G14: ='CON FACTOR DE POTENCIA '!G12 -> 44054 | H14: ='CON FACTOR DE POTENCIA '!S12 -> 30971 | I14: ='CON FACTOR DE POTENCIA '!V29 -> 144093.11 | J14: ='CON FACTOR DE POTENCIA '!V45 -> 897.13567 | K14: =I14-J14 -> 143195.97
F15: Octubre | G15: ='CON FACTOR DE POTENCIA '!G13 -> 45016 | H15: ='CON FACTOR DE POTENCIA '!S13 -> 36764 | I15: ='CON FACTOR DE POTENCIA '!V30 -> 145116.6 | J15: ='CON FACTOR DE POTENCIA '!V46 -> 897.13567 | K15: =I15-J15 -> 144219.47
F16: Noviembre | G16: ='CON FACTOR DE POTENCIA '!G14 -> 33840 | H16: ='CON FACTOR DE POTENCIA '!S14 -> 34684 | I16: ='CON FACTOR DE POTENCIA '!V31 -> 110692.06 | J16: ='CON FACTOR DE POTENCIA '!V47 -> 897.13567 | K16: =I16-J16 -> 109794.92
F17: Diciembre | G17: ='CON FACTOR DE POTENCIA '!G15 -> 30641 | H17: ='CON FACTOR DE POTENCIA '!S15 -> 32376 | I17: ='CON FACTOR DE POTENCIA '!V32 -> 99136.346 | J17: ='CON FACTOR DE POTENCIA '!V48 -> 897.13567 | K17: =I17-J17 -> 98239.21
F18: Ahorro anual | K18: =SUM(K6:K17) -> 1352898
F19: Retorno de inversión | J19: ='COTIZACIÓN '!E11/'tabla general'!K18 -> 2.8969656 | K19: años

Sheet COTIZACIÓN 
C5: Descripción | D5: Total | H5: COSTO SFV | J5: TIPO DE CAMBIO
C6: Tamaño del sistema | E6: ='CON FACTOR DE POTENCIA '!AG5*1000 -> 249240 | F6: W | H6: =E11 -> 3919299 | J6: 18.5
C7: Precio dólar/ watt (18.945) | E7: =H9 -> 0.85
C8: Precio (USD) | D8: USD | E8: =(E6*E7)/1.16 -> 182632.76 | H8: Costo USD / Watt
C9: Subtotal (MXN) | E9: =E8*J6 -> 3378706 | H9: 0.85
C10: IVA (MXN) | E10: =E9*0.16 -> 540592.97
C11: TOTAL (MXN) | E11: =SUM(E9:E10) -> 3919299
C14: UVIE | D14: =25000*1.16 -> 29000
C15: UIIE | D15: =30000*1.16 -> 34800
C16: adecuaciones a la Instalación eléctrica existente
C17: Adaptaciones estructurales
C18: Cambios de transformador | F18: =E11*0.2 -> 783859.8
C19: Ingeniería
C21: Levantamiento tecnico

Sheet ROI
G3: AÑO | H3: AHORRO | I3: AHORRO ACUMULADO | K3: INFLACIÓN ANUAL (5%)
G4: 1 | H4: ='tabla general'!K18 -> 1352898 | I4: =H4 -> 1352898 | K4: 5
G5: 2 | H5: =H4*(1+($K$4/100)) -> 1420542.9 | I5: =I4+H5 -> 2773440.9
G6: 3 | H6: =H5*(1+($K$4/100)) -> 1491570.1 | I6: =I5+H6 -> 4265011
G7: 4 | H7: =H6*(1+($K$4/100)) -> 1566148.6 | I7: =I6+H7 -> 5831159.5
G8: 5 | H8: =H7*(1+($K$4/100)) -> 1644456 | I8: =I7+H8 -> 7475615.5
G9: 6 | H9: =H8*(1+($K$4/100)) -> 1726678.8 | I9: =I8+H9 -> 9202294.3
G10: 7 | H10: =H9*(1+($K$4/100)) -> 1813012.7 | I10: =I9+H10 -> 11015307
G11: 8 | H11: =H10*(1+($K$4/100)) -> 1903663.4 | I11: =I10+H11 -> 12918970
G12: 9 | H12: =H11*(1+($K$4/100)) -> 1998846.5 | I12: =I11+H12 -> 14917817
G13: 10 | H13: =H12*(1+($K$4/100)) -> 2098788.9 | I13: =I12+H13 -> 17016606
G14: 11 | H14: =H13*(1+($K$4/100)) -> 2203728.3 | I14: =I13+H14 -> 19220334
G15: 12 | H15: =H14*(1+($K$4/100)) -> 2313914.7 | I15: =I14+H15 -> 21534249
G16: 13 | H16: =H15*(1+($K$4/100)) -> 2429610.5 | I16: =I15+H16 -> 23963859
... G28: 25 | H28: =H27*(1+($K$4/100)) -> 4363231.3 | I28: =I27+H28 -> 64569897
